openbt/__init__.py
openbt/openbt.py
openbt-0.0.5.dist-info/LICENSE
openbt-0.0.5.dist-info/METADATA
openbt-0.0.5.dist-info/WHEEL
openbt-0.0.5.dist-info/top_level.txt
openbt-0.0.5.dist-info/RECORD
