Metadata-Version: 2.1
Name: openbt
Version: 0.0.5
Summary: the Python interface for Dr. Matthew Pratola's OpenBT project - allows the user to perform BART (Bayesian Additive Regression Trees) fits and predictions on datasets.
Home-page: https://github.com/cavan33/openbt_py
Author: Clark Van Lieshout
Author-email: clarkvan33@gmail.com
License: UNKNOWN
Project-URL: ROpenBT, https://bitbucket.org/mpratola/openbt/wiki/Home
Project-URL: Zoltan Puha's class, https://github.com/Nth-iteration-labs/openbt-python
Platform: UNKNOWN
Classifier: Programming Language :: Python :: 3
Classifier: License :: OSI Approved :: GNU Affero General Public License v3
Classifier: Operating System :: OS Independent
Classifier: Development Status :: 3 - Alpha
Classifier: Intended Audience :: Science/Research
Classifier: Natural Language :: English
Requires-Python: >=3.0
License-File: LICENSE
Requires-Dist: invoke
Requires-Dist: numpy
Requires-Dist: sklearn
Requires-Dist: pathlib
Requires-Dist: pandas
Requires-Dist: matplotlib
